mlflow_log_module-1.0.0.dist-info/licenses/LICENSE.lic
model_transfer/__init__.py
model_transfer/mlflow_log_module.py
mlflow_log_module-1.0.0.dist-info/METADATA
mlflow_log_module-1.0.0.dist-info/WHEEL
mlflow_log_module-1.0.0.dist-info/top_level.txt
mlflow_log_module-1.0.0.dist-info/RECORD
