Metadata-Version: 2.4
Name: mlflow_log_module
Version: 1.0.0
Summary: A package to log the params, metrics and artifacts to mlflow ui.
Author: Radhika Menon
Author-email: Radhika.Menon@cognizant.com
Classifier: Programming Language :: Python :: 3
Classifier: License :: OSI Approved :: MIT License
Classifier: Operating System :: OS Independent
Requires-Python: >=3.6
License-File: LICENSE.lic
Dynamic: author
Dynamic: author-email
Dynamic: classifier
Dynamic: license-file
Dynamic: requires-python
Dynamic: summary
